mujoco/msh2obj.py
mujoco/minimize.py
mujoco/gl_context.py
mujoco/_constants.cpython-313-x86_64-linux-gnu.so
mujoco/renderer_test.py
mujoco/_rollout.cpython-313-x86_64-linux-gnu.so
mujoco/msh2obj_test.py
mujoco/memory_leak_test.py
mujoco/_render.cpython-313-x86_64-linux-gnu.so
mujoco/_errors.cpython-313-x86_64-linux-gnu.so
mujoco/specs_test.py
mujoco/bindings_test.py
mujoco/_structs.cpython-313-x86_64-linux-gnu.so
mujoco/rollout_test.py
mujoco/render_test.py
mujoco/_functions.cpython-313-x86_64-linux-gnu.so
mujoco/_enums.cpython-313-x86_64-linux-gnu.so
mujoco/viewer.py
mujoco/__init__.py
mujoco/_specs.cpython-313-x86_64-linux-gnu.so
mujoco/_simulate.cpython-313-x86_64-linux-gnu.so
mujoco/minimize_test.py
mujoco/_callbacks.cpython-313-x86_64-linux-gnu.so
mujoco/renderer.py
mujoco/rollout.py
mujoco/libmujoco.so.3.4.0
mujoco/viewer_test.py
mujoco/cgl/cgl.py
mujoco/cgl/__init__.py
mujoco/egl/egl_ext.py
mujoco/egl/__init__.py
mujoco/include/mujoco/materialAPI.h
mujoco/include/mujoco/mjsan.h
mujoco/include/mujoco/mujoco.h
mujoco/include/mujoco/mjui.h
mujoco/include/mujoco/mjvisualize.h
mujoco/include/mujoco/mjdata.h
mujoco/include/mujoco/siteAPI.h
mujoco/include/mujoco/tendon.h
mujoco/include/mujoco/keyframe.h
mujoco/include/mujoco/utils.h
mujoco/include/mujoco/sceneAPI.h
mujoco/include/mujoco/writer.h
mujoco/include/mujoco/actuator.h
mujoco/include/mujoco/mjplugin.h
mujoco/include/mujoco/imageableAPI.h
mujoco/include/mujoco/mjmacro.h
mujoco/include/mujoco/meshCollisionAPI.h
mujoco/include/mujoco/layer_sink.h
mujoco/include/mujoco/collisionAPI.h
mujoco/include/mujoco/usd.h
mujoco/include/mujoco/mjthread.h
mujoco/include/mujoco/mjexport.h
mujoco/include/mujoco/mjxmacro.h
mujoco/include/mujoco/mjtnum.h
mujoco/include/mujoco/jointAPI.h
mujoco/include/mujoco/api.h
mujoco/include/mujoco/mjspec.h
mujoco/include/mujoco/mjrender.h
mujoco/include/mujoco/tokens.h
mujoco/include/mujoco/mjmodel.h
mujoco/introspect/enums.py
mujoco-3.4.0.dist-info/RECORD
mujoco-3.4.0.dist-info/WHEEL
mujoco-3.4.0.dist-info/METADATA
mujoco-3.4.0.dist-info/top_level.txt
mujoco-3.4.0.dist-info/licenses/LICENSE
mujoco-3.4.0.dist-info/licenses/LICENSES_THIRD_PARTY.md
