Metadata-Version: 2.4
Name: mujoco
Version: 3.4.0
Summary: MuJoCo Physics Simulator
Author-email: Google DeepMind <mujoco@deepmind.com>
License-Expression: Apache-2.0
Project-URL: Homepage, https://github.com/google-deepmind/mujoco
Project-URL: Documentation, https://mujoco.readthedocs.io/en/3.4.0
Project-URL: Repository, https://github.com/google-deepmind/mujoco
Project-URL: Changelog, https://mujoco.readthedocs.io/en/3.4.0/changelog.html
Classifier: Development Status :: 5 - Production/Stable
Classifier: Intended Audience :: Developers
Classifier: Intended Audience :: Science/Research
Classifier: Natural Language :: English
Classifier: Programming Language :: Python :: 3
Classifier: Programming Language :: Python :: 3.9
Classifier: Programming Language :: Python :: 3.10
Classifier: Programming Language :: Python :: 3.11
Classifier: Programming Language :: Python :: 3.12
Classifier: Topic :: Scientific/Engineering
Requires-Python: >=3.9
License-File: LICENSE
License-File: LICENSES_THIRD_PARTY.md
Requires-Dist: absl-py
Requires-Dist: etils[epath]
Requires-Dist: glfw
Requires-Dist: numpy
Requires-Dist: pyopengl
Provides-Extra: usd
Requires-Dist: usd-core; extra == "usd"
Requires-Dist: pillow; extra == "usd"
Dynamic: description
Dynamic: description-content-type
Dynamic: license-file
